cbnmplib/__init__.py
cbnmplib/communicate.py
cbnmplib/install.py
cbnmplib/pipeline.py
cbnmplib-1.0.11.dist-info/METADATA
cbnmplib-1.0.11.dist-info/WHEEL
cbnmplib-1.0.11.dist-info/top_level.txt
cbnmplib-1.0.11.dist-info/RECORD
