Metadata-Version: 2.1
Name: cbnmplib
Version: 1.0.11
Summary: chrome browser native messaging pipeline library
Home-page: UNKNOWN
Author: UNKNOWN
Author-email: UNKNOWN
License: MIT
Platform: UNKNOWN
Classifier: Programming Language :: Python :: 3
Classifier: License :: OSI Approved :: MIT License
Classifier: Operating System :: OS Independent
